pinatapy/__init__.py
test/__init__.py
test/test_pinatapy.py
pinatapy_vourhey-0.2.0.dist-info/LICENSE
pinatapy_vourhey-0.2.0.dist-info/METADATA
pinatapy_vourhey-0.2.0.dist-info/WHEEL
pinatapy_vourhey-0.2.0.dist-info/top_level.txt
pinatapy_vourhey-0.2.0.dist-info/RECORD
