Metadata-Version: 2.1
Name: pinatapy-vourhey
Version: 0.2.0
Summary: Non-official Pinata.cloud library
Home-page: https://github.com/vourhey/pinatapy
Author: Vadim Manaenko
Author-email: vadim.razorq@gmail.com
Classifier: Programming Language :: Python :: 3
Classifier: License :: OSI Approved :: BSD License
Classifier: Operating System :: OS Independent
Requires-Python: >=3.6
License-File: LICENSE
Requires-Dist: requests
